Metadata-Version: 1.0
Name: big-config
Version: 0.3.1
Summary: Handles a more complex configuration file structure
Home-page: http://github.com/vladblindu/
Author: Vlad Blindu
Author-email: vlad.blindu@bbsmedia.ro
License: BSD
Platform: UNKNOWN
